[
  {
    "ID": 1,
    "name": "Virtus",
    "FP": 5,
    "Cell":
    [
      { "value": 4, "color": "NULL" }, { "value": 0, "color": "NULL" }, { "value": 2, "color": "NULL" }, { "value": 5, "color": "NULL" }, { "value": 0, "color": "GREEN" },
      { "value": 0, "color": "NULL" }, { "value": 0, "color": "NULL" }, { "value": 6, "color": "NULL" }, { "value": 0, "color": "GREEN" }, { "value": 2, "color": "NULL" },
      { "value": 0, "color": "NULL" }, { "value": 3, "color": "NULL" }, { "value": 0, "color": "GREEN" }, { "value": 4, "color": "NULL" }, { "value": 0, "color": "NULL" },
      { "value": 5, "color": "NULL" }, { "value": 0, "color": "GREEN" }, { "value": 1, "color": "NULL" }, { "value": 0, "color": "NULL" }, { "value": 0, "color": "NULL" }
    ]
  },

  {
    "ID": 2,
    "name": "Symphony of Light",
    "FP": 6,
    "Cell":
    [
      { "value": 0, "color": "NULL" }, { "value": 0, "color": "NULL" }, { "value": 0, "color": "NULL" }, { "value": 0, "color": "NULL" }, { "value": 0, "color": "NULL" },
      { "value": 0, "color": "NULL" }, { "value": 0, "color": "NULL" }, { "value": 0, "color": "NULL" }, { "value": 0, "color": "NULL" }, { "value": 0, "color": "NULL" },
      { "value": 0, "color": "NULL" }, { "value": 0, "color": "NULL" }, { "value": 0, "color": "NULL" }, { "value": 0, "color": "NULL" }, { "value": 0, "color": "NULL" },
      { "value": 0, "color": "NULL" }, { "value": 0, "color": "NULL" }, { "value": 0, "color": "NULL" }, { "value": 0, "color": "NULL" }, { "value": 0, "color": "NULL" }
    ]
  },

  {
    "ID": 1,
    "name": "Virtus",
    "FP": 5,
    "Cell":
    [
      { "value": 0, "color": "NULL" }, { "value": 0, "color": "NULL" }, { "value": 0, "color": "NULL" }, { "value": 0, "color": "NULL" }, { "value": 0, "color": "NULL" },
      { "value": 0, "color": "NULL" }, { "value": 0, "color": "NULL" }, { "value": 0, "color": "NULL" }, { "value": 0, "color": "NULL" }, { "value": 0, "color": "NULL" },
      { "value": 0, "color": "NULL" }, { "value": 0, "color": "NULL" }, { "value": 0, "color": "NULL" }, { "value": 0, "color": "NULL" }, { "value": 0, "color": "NULL" },
      { "value": 0, "color": "NULL" }, { "value": 0, "color": "NULL" }, { "value": 0, "color": "NULL" }, { "value": 0, "color": "NULL" }, { "value": 0, "color": "NULL" }
    ]
  },

  {
    "ID": 1,
    "name": "Virtus",
    "FP": 5,
    "Cell":
    [
      { "value": 0, "color": "NULL" }, { "value": 0, "color": "NULL" }, { "value": 0, "color": "NULL" }, { "value": 0, "color": "NULL" }, { "value": 0, "color": "NULL" },
      { "value": 0, "color": "NULL" }, { "value": 0, "color": "NULL" }, { "value": 0, "color": "NULL" }, { "value": 0, "color": "NULL" }, { "value": 0, "color": "NULL" },
      { "value": 0, "color": "NULL" }, { "value": 0, "color": "NULL" }, { "value": 0, "color": "NULL" }, { "value": 0, "color": "NULL" }, { "value": 0, "color": "NULL" },
      { "value": 0, "color": "NULL" }, { "value": 0, "color": "NULL" }, { "value": 0, "color": "NULL" }, { "value": 0, "color": "NULL" }, { "value": 0, "color": "NULL" }
    ]
  },

]